{
    "title": "The Shadows",
    "publisher": "CBC",
    "link": "https://www.cbc.ca/radio/podcasts/the-shadows/https://www.cbc.ca/radiointeractives/podcasts/the-shadows",
    "rssFeed": "https://www.cbc.ca/podcasting/includes/theshadows.xml",
    "image": "https://www.cbc.ca/radio/podcasts/images/promo-theshadows-1400x1400.jpg",
    "description": "Kaitlin Prest, creator and host of the Prix-Italia winner The Heart, presents the first audio fiction from CBC Podcasts. The Shadows is a story about the anatomy of a relationship: a crush, a choice,  ...",
    "categories": [
        "Arts"
    ],
    "slug": "cbc-the-shadows",
    "episodes": [
        {
            "title": "Episode 1: Romantic",
            "subtitle": "\"When love beckons to you, follow [it]\n...\nAnd when [its] wings enfold you yield to [it],\nThough the sword hidden among [its] pinions may wound you.\n...\nFor even as love crowns you so shall [it] crucify you.\nEven as [it] is for your growth so is [it] for your pruning.\" - Kahlil Gibran, On Love",
            "image": "https://www.cbc.ca/radio/podcasts/images/promo-theshadows-1400x1400.jpg",
            "datePublished": "Mon, 24 Sep 2018 11:59:00 EDT",
            "description": "\"When love beckons to you, follow [it]\n...\nAnd when [its] wings enfold you yield to [it],\nThough the sword hidden among [its] pinions may wound you.\n...\nFor even as love crowns you so shall [it] crucify you.\nEven as [it] is for your growth so is [it] for your pruning.\" - Kahlil Gibran, On Love",
            "duration": "00:44:48",
            "sourceUrl": "https://cbc.mc.tritondigital.com/CBC_THESHADOWS_P/media/theshadows-lvL6JcCe-20180924.mp3",
            "epNo": "1",
            "podcast": "cbc-the-shadows",
            "slug": "cbc-the-shadows?episode=2018-09-24-episode-1-romantic"
        },
        {
            "title": "Episode 2: Realist",
            "subtitle": "\"These pains you feel are messengers. Listen to them.\" - Rumi",
            "image": "https://www.cbc.ca/radio/podcasts/images/promo-theshadows-1400x1400.jpg",
            "datePublished": "Mon, 24 Sep 2018 11:58:00 EDT",
            "description": "\"These pains you feel are messengers. Listen to them.\" - Rumi",
            "duration": "00:36:34",
            "sourceUrl": "https://cbc.mc.tritondigital.com/CBC_THESHADOWS_P/media/theshadows-1IuI90th-20180924.mp3",
            "epNo": "2",
            "podcast": "cbc-the-shadows",
            "slug": "cbc-the-shadows?episode=2018-09-24-episode-2-realist"
        },
        {
            "title": "Episode 3: Sweater",
            "subtitle": "\"Love is being there every day, to keep someone warm, to hold them through the night, to make them feel cozy.\" - Sweater",
            "image": "https://www.cbc.ca/radio/podcasts/images/promo-theshadows-1400x1400.jpg",
            "datePublished": "Mon, 24 Sep 2018 11:57:00 EDT",
            "description": "\"Love is being there every day, to keep someone warm, to hold them through the night, to make them feel cozy.\" - Sweater",
            "duration": "00:32:07",
            "sourceUrl": "https://cbc.mc.tritondigital.com/CBC_THESHADOWS_P/media/theshadows-8C1Jy0ij-20180924.mp3",
            "epNo": "3",
            "podcast": "cbc-the-shadows",
            "slug": "cbc-the-shadows?episode=2018-09-24-episode-3-sweater"
        },
        {
            "title": "Episode 4: Decision",
            "subtitle": "\"Romantics value intensity over stability. Realists value security over passion. But both are often disappointed, for few people can live happily at either extreme.\" - Esther Perel, Mating in Captivity",
            "image": "https://www.cbc.ca/radio/podcasts/images/promo-theshadows-1400x1400.jpg",
            "datePublished": "Mon, 24 Sep 2018 11:56:00 EDT",
            "description": "\"Romantics value intensity over stability. Realists value security over passion. But both are often disappointed, for few people can live happily at either extreme.\" - Esther Perel, Mating in Captivity",
            "duration": "00:33:37",
            "sourceUrl": "https://cbc.mc.tritondigital.com/CBC_THESHADOWS_P/media/theshadows-KkP5bVy1-20180924.mp3",
            "epNo": "4",
            "podcast": "cbc-the-shadows",
            "slug": "cbc-the-shadows?episode=2018-09-24-episode-4-decision"
        },
        {
            "title": "Episode 5: An Argument That Should Be Simple.",
            "subtitle": "\"A decided heart looks for a solution. An undecided heart looks for a way out.\" - Tom, a regular at the Bramasole Diner",
            "image": "https://www.cbc.ca/radio/podcasts/images/promo-theshadows-1400x1400.jpg",
            "datePublished": "Mon, 24 Sep 2018 11:55:00 EDT",
            "description": "\"A decided heart looks for a solution. An undecided heart looks for a way out.\" - Tom, a regular at the Bramasole Diner",
            "duration": "00:21:42",
            "sourceUrl": "https://cbc.mc.tritondigital.com/CBC_THESHADOWS_P/media/theshadows-CmG3eJjl-20180924.mp3",
            "epNo": "5",
            "podcast": "cbc-the-shadows",
            "slug": "cbc-the-shadows?episode=2018-09-24-episode-5-an-argument-that-should-be-simple"
        },
        {
            "title": "Episode 6: End",
            "subtitle": "\"With every commitment there is much that it rejects. Much that it excludes.\" - Adam Phillips, Unforbidden Pleasures",
            "image": "https://www.cbc.ca/radio/podcasts/images/promo-theshadows-1400x1400.jpg",
            "datePublished": "Mon, 24 Sep 2018 11:54:00 EDT",
            "description": "\"With every commitment there is much that it rejects. Much that it excludes.\" - Adam Phillips, Unforbidden Pleasures",
            "duration": "00:31:44",
            "sourceUrl": "https://cbc.mc.tritondigital.com/CBC_THESHADOWS_P/media/theshadows-po8XzLmZ-20180924.mp3",
            "epNo": "6",
            "podcast": "cbc-the-shadows",
            "slug": "cbc-the-shadows?episode=2018-09-24-episode-6-end"
        }
    ]
}